LICENSE
README.md
lyyre.py
setup.py
lyyre.egg-info/PKG-INFO
lyyre.egg-info/SOURCES.txt
lyyre.egg-info/dependency_links.txt
lyyre.egg-info/top_level.txt