Metadata-Version: 2.1
Name: lyyre
Version: 2.2
Summary: userfull application for  lyy
Author: lyy
Author-email: 
License: MIT
License-File: LICENSE
